project9_Arithmetic circuits for digital systems/02_add_sub.v
module add_sub
#(parameter DIVIDER=  100000)
(
    input clk,rst,
    input [15:0] sw, 
    input [2:0]btn,
    output reg [3:0] led,
    output [2:0]RGB0,
    output reg[6:0] D1_SEG, 
    output reg [3:0] D1_AN
    );

///////////8 bit operater part/////////////////
reg [7:0] op1, op2;

always @ (posedge(clk)) begin
if (rst) begin  op1<= 0; 
                op2<= 0;
         end
else     begin
    if (btn[0]) op1 <= sw;
    if (btn[1]) op2 <= sw;
         end
end
//////////////add/ subtractor////////////////////
reg [7:0] bin_data;
wire op2_2;
assign op2_2 = (op2^{8{btn[2]}} );
always @(*)begin
     bin_data = op1 + op2_2 + btn[2];
end
///////////overflow underflow detect//////////////////////
wire [7:0]G,P;
wire [1:0]Cout;
wire Cin;
assign P = op1 | op2_2;
assign G = op1 & op2_2;
assign Cin = btn[2];

assign Cout[0] = G[6]|(P[6]&G[5])|(P[6]&P[5]&G[4])|(P[6]&P[5]&P[4]&G[3])|(P[6]&P[5]&P[4]&P[3]&G[2])|
                     (P[6]&P[5]&P[4]&P[3]&P[2]&G[1])| (P[6]&P[5]&P[4]&P[3]&P[2]&P[1]&G[0])| 
                     (P[6]&P[5]&P[4]&P[3]&P[2]&P[1]&P[0]&Cin);

assign Cout[1]   = G[7]|(P[7]&G[6])|(P[7]&P[6]&G[5])|(P[7]&P[6]&P[5]&G[4])|(P[7]&P[6]&P[5]&P[4]&G[3])|
                     (P[7]&P[6]&P[5]&P[4]&P[3]&G[2])| (P[7]&P[6]&P[5]&P[4]&P[3]&P[2]&G[1])| 
                     (P[7]&P[6]&P[5]&P[4]&P[3]&P[2]&P[1]&G[0])|(P[7]&P[6]&P[5]&P[4]&P[3]&P[2]&P[1]&P[0]&Cin);

assign RGB0[0] = Cout[0] ^ Cout[1] ; //when overflow or underflow, red light turn on.
///////////////negetive result show up/////////////////
reg [7:0]result ;
always @(*)begin
   if(!bin_data[7])begin result = bin_data;         led[0] = 1'b1 ;end
   else            begin result = ~bin_data + 1'b1; led[0] = 1'b0 ;end
end
/////////////// bin_data to BCD/////////////////
reg [11:0]bcd;
integer i;
always @(*)begin
  bcd=0;		 	
    for (i=0;i<8;i=i+1) begin					//Iterate once for each bit in input number
        if (bcd[3:0] >= 5)  bcd[3:0]  = bcd[3:0] + 3;		//If any BCD digit is >= 5, add three
	    if (bcd[7:4] >= 5)  bcd[7:4]  = bcd[7:4] + 3;
	    if (bcd[11:8] >= 5) bcd[11:8] = bcd[11:8] + 3;
	    bcd = {bcd[10:0],result[7-i]};				//Shift one bit, and shift in proper bit from input 
    end
end

//////////////////////////////////////////////////
////////////////// 7-seg display/////////////////
////////////2-bit counter///////////////
reg [$clog2(DIVIDER):0]cnt;
always @(posedge clk, posedge rst)begin
    if(rst)cnt <= 0;
    else cnt = cnt + 1;
end
////////////2-bit counter///////////////
wire [1:0] S;
reg [3:0]data;
assign S = cnt[$clog2(DIVIDER):$clog2(DIVIDER)-1];
always @(*)begin
    case(S)
    2'b00: begin data = bcd[3:0];  D1_AN= 4'b1110;end
    2'b01: begin data = bcd[7:4];  D1_AN= 4'b1101;end
    2'b10: begin data = bcd[11:8]; D1_AN= 4'b1011;end
    2'b11: begin data = 4'd0;      D1_AN= 4'b0111;end
    endcase
end
always @ (*)
begin
    case(data)
    0: D1_SEG = 7'b100_0000;	
    1: D1_SEG = 7'b111_1001;
    2: D1_SEG = 7'b010_0100;
    3: D1_SEG = 7'b011_0000;
    4: D1_SEG = 7'b001_1001;
    5: D1_SEG = 7'b001_0010;
    6: D1_SEG = 7'b000_0010;
    7: D1_SEG = 7'b111_1000;
    8: D1_SEG = 7'b000_0000;
    9: D1_SEG = 7'b001_0000;
    default: D1_SEG = 7'b100_0000;	
    endcase
end
endmodule

project9_Arithmetic circuits for digital systems/tb.v
`timescale 1ns/1ps
module tb;
reg clk,rst,op;
reg [7:0]A,B;
reg [3:1] data;
wire[7:0] result;
add_sub c1(clk,rst,{B,A},data,result);

//always #5clk=~clk;
initial 
    begin
        $dumpfile("02.vcd");
        $dumpvars;
        clk=0;
        rst =0;
        A = 0;
        #3 rst=1;
        #10 rst=0;
        data = 0010;
        #10 A = 3; B = 4;data = 3'b000; 
        #10 A = 6; B = 7;data = 3'b111; 
        #10 A = 5; B = 8;data = 3'b110; 
        #10 A = 2; B = 6;data = 3'b111; 
        #10 A = 0; B = 10;data = 3'b110; 
        #10 A = 9; B = 3;data = 3'b111; 

      
        //#20 $stop;
end
endmodule

project9_Arithmetic circuits for digital systems/02.vcd
$date
	Thu May 19 22:27:58 2022
$end
$version
	Icarus Verilog
$end
$timescale
	1ps
$end
$scope module tb $end
$var wire 8 ! result [7:0] $end
$var reg 8 " A [7:0] $end
$var reg 8 # B [7:0] $end
$var reg 1 $ clk $end
$var reg 3 % data [3:1] $end
$var reg 1 & rst $end
$scope module c1 $end
$var wire 3 ' btn [3:1] $end
$var wire 1 $ clk $end
$var wire 8 ( op1 [7:0] $end
$var wire 8 ) op2 [7:0] $end
$var wire 1 & rst $end
$var wire 16 * sw [15:0] $end
$var reg 8 + result [7:0] $end
$upscope $end
$upscope $end
$enddefinitions $end
#0
$dumpvars
bx +
bx00000000 *
bx )
bx (
bx '
0&
bx %
0$
bx #
b0 "
bx !
$end
#3000
1&
#13000
b10 %
b10 '
0&
#23000
b100 )
b11111011 (
b111 !
b111 +
b0 %
b0 '
b100 #
b10000000011 *
b11 "
#33000
b11111000 )
b11111000 (
b11111111 !
b11111111 +
b111 %
b111 '
b111 #
b11100000110 *
b110 "
#43000
b1000 )
b11110111 (
b1101 !
b1101 +
b110 %
b110 '
b1000 #
b100000000101 *
b101 "
#53000
b11111001 )
b11111001 (
b11111100 !
b11111100 +
b111 %
b111 '
b110 #
b11000000010 *
b10 "
#63000
b1010 )
b11110101 (
b1010 !
b1010 +
b110 %
b110 '
b1010 #
b101000000000 *
b0 "
#73000
b11111100 )
b11111100 (
b110 !
b110 +
b111 %
b111 '
b11 #
b1100001001 *
b1001 "
