project4_ Basic Combinational Building Blocks/03encoder_4_2.v
module encoder_4_2(
    input [3:0] I,
	input Ein,
	output reg [1:0] Y,
	output reg GS, 
	output reg Eout
);
always @ (I, Ein)
begin
    if(Ein == 1) begin
        if (I[3] == 1)
            Y <= 2'd3;
        else if (I[2] == 1)
            Y <= 2'd2;
        else if (I[1] == 1)
            Y <= 2'd1;
        else
            Y <= 2'd0;
    end
    else
        Y = 2'd0;
end

always @ (I, Ein)
begin
    if (Ein == 1 && I == 0)
        Eout <= 1'b1;
    else
        Eout <= 1'b0;
end

always @ (I, Ein)
begin
    if (Ein == 1 && I != 0)
        GS <= 1'b1;
    else
        GS <= 1'b0;
end

endmodule

project4_ Basic Combinational Building Blocks/03encoder_4_2_tb.v
`timescale 1ns / 1ps
module encoder_4_2_tb;

reg [3:0] I;
reg Ein;
wire  [1:0] Y;
wire GS,Eout;

encoder_4_2 name(I,Ein,Y,GS,Eout);

integer k;
initial begin
    $dumpfile("encoder_4_2.vcd");
    $dumpvars(0,name);
    Ein = 0; I = 0000;
    #5 I = 0010;
    #5 Ein =1;
    for(k=0; k < 16; k=k+1) begin
        I = k;
        #5; // wait 10ns
    end
end
endmodule

project4_ Basic Combinational Building Blocks/encoder_4_2.vcd
$date
	Mon May  2 15:27:04 2022
$end
$version
	Icarus Verilog
$end
$timescale
	1ps
$end
$scope module encoder_4_2_tb $end
$scope module name $end
$var wire 1 ! Ein $end
$var wire 4 " I [3:0] $end
$var reg 1 # Eout $end
$var reg 1 $ GS $end
$var reg 2 % Y [1:0] $end
$upscope $end
$upscope $end
$enddefinitions $end
#0
$dumpvars
b0 %
0$
0#
b0 "
0!
$end
#5000
b1010 "
#10000
1#
b0 "
1!
#15000
0#
1$
b1 "
#20000
b1 %
b10 "
#25000
b11 "
#30000
b10 %
b100 "
#35000
b101 "
#40000
b110 "
#45000
b111 "
#50000
b11 %
b1000 "
#55000
b1001 "
#60000
b1010 "
#65000
b1011 "
#70000
b1100 "
#75000
b1101 "
#80000
b1110 "
#85000
b1111 "
