project4_ Basic Combinational Building Blocks/mux_4_2.v
module mux_4_2(
    input [1:0] I0, I1,I2,I3,
    input [1:0] sel,
    output [1:0]Y
);
reg [1:0] tmp;
always @( I0, I1,I2,I3,sel)begin
    case(sel)
    2'b00: tmp <= I0;
    2'b01: tmp <= I1;
    2'b10: tmp <= I2;
    2'b11: tmp <= I3;
    default tmp<= 2'b00;
    endcase
end    
assign Y = tmp;
endmodule

project4_ Basic Combinational Building Blocks/mux_4_2_tb.v
// simulation
`timescale 1ns / 1ps

module mux_4_2_tb;

// inputs
reg [1:0] I0, I1, I2, I3;
reg [1:0] sel;

// outputs
wire [1:0] Y;

// connect test signals to our mux
mux_4_2 name (
    .I0(I0),
    .I1(I1),
    .I2(I2),
    .I3(I3),
    .sel(sel),
    .Y(Y)
);

integer k;
initial begin
    $dumpfile("mux_4_2.vcd");
    $dumpvars(0,name);
    sel = 2'b00;
    for(k=0; k < 256; k=k+1) begin
        {I3, I2, I1, I0} = k;
        #10;
    end
    
    sel = 2'b01;
    for(k=0; k < 256; k=k+1) begin
        {I3, I2, I1, I0} = k;
        #10;
    end
    
    sel = 2'b10;
    for(k=0; k < 256; k=k+1) begin
        {I3, I2, I1, I0} = k;
        #10;
    end
    
    sel = 2'b11;
    for(k=0; k < 256; k=k+1) begin
        {I3, I2, I1, I0} = k;
        #10;
    end
    
    sel = 2'b1z;
    for(k=0; k < 256; k=k+1) begin
        {I3, I2, I1, I0} = k;
        #10;
    end
    
    sel = 2'b1x;
    for(k=0; k < 256; k=k+1) begin
        {I3, I2, I1, I0} = k;
        #10;
    end
    $finish;
end

endmodule

project4_ Basic Combinational Building Blocks/mux_4_2.vcd
$date
	Wed Mar 30 14:40:06 2022
$end
$version
	Icarus Verilog
$end
$timescale
	1ps
$end
$scope module mux_4_2_tb $end
$scope module name $end
$var wire 2 ! I0 [1:0] $end
$var wire 2 " I1 [1:0] $end
$var wire 2 # I2 [1:0] $end
$var wire 2 $ I3 [1:0] $end
$var wire 2 % Y [1:0] $end
$var wire 2 & sel [1:0] $end
$var reg 2 ' tmp [1:0] $end
$upscope $end
$upscope $end
$enddefinitions $end
#0
$dumpvars
b0 '
b0 &
b0 %
b0 $
b0 #
b0 "
b0 !
$end
#10000
b1 %
b1 '
b1 !
#20000
b10 %
b10 '
b10 !
#30000
b11 %
b11 '
b11 !
#40000
b0 %
b0 '
b1 "
b0 !
#50000
b1 %
b1 '
b1 !
#60000
b10 %
b10 '
b10 !
#70000
b11 %
b11 '
b11 !
#80000
b0 %
b0 '
b10 "
b0 !
#90000
b1 %
b1 '
b1 !
#100000
b10 %
b10 '
b10 !
#110000
b11 %
b11 '
b11 !
#120000
b0 %
b0 '
b11 "
b0 !
#130000
b1 %
b1 '
b1 !
#140000
b10 %
b10 '
b10 !
#150000
b11 %
b11 '
b11 !
#160000
b0 %
b0 '
b1 #
b0 "
b0 !
#170000
b1 %
b1 '
b1 !
#180000
b10 %
b10 '
b10 !
#190000
b11 %
b11 '
b11 !
#200000
b0 %
b0 '
b1 "
b0 !
#210000
b1 %
b1 '
b1 !
#220000
b10 %
b10 '
b10 !
#230000
b11 %
b11 '
b11 !
#240000
b0 %
b0 '
b10 "
b0 !
#250000
b1 %
b1 '
b1 !
#260000
b10 %
b10 '
b10 !
#270000
b11 %
b11 '
b11 !
#280000
b0 %
b0 '
b11 "
b0 !
#290000
b1 %
b1 '
b1 !
#300000
b10 %
b10 '
b10 !
#310000
b11 %
b11 '
b11 !
#320000
b0 %
b0 '
b10 #
b0 "
b0 !
#330000
b1 %
b1 '
b1 !
#340000
b10 %
b10 '
b10 !
#350000
b11 %
b11 '
b11 !
#360000
b0 %
b0 '
b1 "
b0 !
#370000
b1 %
b1 '
b1 !
#380000
b10 %
b10 '
b10 !
#390000
b11 %
b11 '
b11 !
#400000
b0 %
b0 '
b10 "
b0 !
#410000
b1 %
b1 '
b1 !
#420000
b10 %
b10 '
b10 !
#430000
b11 %
b11 '
b11 !
#440000
b0 %
b0 '
b11 "
b0 !
#450000
b1 %
b1 '
b1 !
#460000
b10 %
b10 '
b10 !
#470000
b11 %
b11 '
b11 !
#480000
b0 %
b0 '
b11 #
b0 "
b0 !
#490000
b1 %
b1 '
b1 !
#500000
b10 %
b10 '
b10 !
#510000
b11 %
b11 '
b11 !
#520000
b0 %
b0 '
b1 "
b0 !
#530000
b1 %
b1 '
b1 !
#540000
b10 %
b10 '
b10 !
#550000
b11 %
b11 '
b11 !
#560000
b0 %
b0 '
b10 "
b0 !
#570000
b1 %
b1 '
b1 !
#580000
b10 %
b10 '
b10 !
#590000
b11 %
b11 '
b11 !
#600000
b0 %
b0 '
b11 "
b0 !
#610000
b1 %
b1 '
b1 !
#620000
b10 %
b10 '
b10 !
#630000
b11 %
b11 '
b11 !
#640000
b0 %
b0 '
b1 $
b0 #
b0 "
b0 !
#650000
b1 %
b1 '
b1 !
#660000
b10 %
b10 '
b10 !
#670000
b11 %
b11 '
b11 !
#680000
b0 %
b0 '
b1 "
b0 !
#690000
b1 %
b1 '
b1 !
#700000
b10 %
b10 '
b10 !
#710000
b11 %
b11 '
b11 !
#720000
b0 %
b0 '
b10 "
b0 !
#730000
b1 %
b1 '
b1 !
#740000
b10 %
b10 '
b10 !
#750000
b11 %
b11 '
b11 !
#760000
b0 %
b0 '
b11 "
b0 !
#770000
b1 %
b1 '
b1 !
#780000
b10 %
b10 '
b10 !
#790000
b11 %
b11 '
b11 !
#800000
b0 %
b0 '
b1 #
b0 "
b0 !
#810000
b1 %
b1 '
b1 !
#820000
b10 %
b10 '
b10 !
#830000
b11 %
b11 '
b11 !
#840000
b0 %
b0 '
b1 "
b0 !
#850000
b1 %
b1 '
b1 !
#860000
b10 %
b10 '
b10 !
#870000
b11 %
b11 '
b11 !
#880000
b0 %
b0 '
b10 "
b0 !
#890000
b1 %
b1 '
b1 !
#900000
b10 %
b10 '
b10 !
#910000
b11 %
b11 '
b11 !
#920000
b0 %
b0 '
b11 "
b0 !
#930000
b1 %
b1 '
b1 !
#940000
b10 %
b10 '
b10 !
#950000
b11 %
b11 '
b11 !
#960000
b0 %
b0 '
b10 #
b0 "
b0 !
#970000
b1 %
b1 '
b1 !
#980000
b10 %
b10 '
b10 !
#990000
b11 %
b11 '
b11 !
#1000000
b0 %
b0 '
b1 "
b0 !
#1010000
b1 %
b1 '
b1 !
#1020000
b10 %
b10 '
b10 !
#1030000
b11 %
b11 '
b11 !
#1040000
b0 %
b0 '
b10 "
b0 !
#1050000
b1 %
b1 '
b1 !
#1060000
b10 %
b10 '
b10 !
#1070000
b11 %
b11 '
b11 !
#1080000
b0 %
b0 '
b11 "
b0 !
#1090000
b1 %
b1 '
b1 !
#1100000
b10 %
b10 '
b10 !
#1110000
b11 %
b11 '
b11 !
#1120000
b0 %
b0 '
b11 #
b0 "
b0 !
#1130000
b1 %
b1 '
b1 !
#1140000
b10 %
b10 '
b10 !
#1150000
b11 %
b11 '
b11 !
#1160000
b0 %
b0 '
b1 "
b0 !
#1170000
b1 %
b1 '
b1 !
#1180000
b10 %
b10 '
b10 !
#1190000
b11 %
b11 '
b11 !
#1200000
b0 %
b0 '
b10 "
b0 !
#1210000
b1 %
b1 '
b1 !
#1220000
b10 %
b10 '
b10 !
#1230000
b11 %
b11 '
b11 !
#1240000
b0 %
b0 '
b11 "
b0 !
#1250000
b1 %
b1 '
b1 !
#1260000
b10 %
b10 '
b10 !
#1270000
b11 %
b11 '
b11 !
#1280000
b0 %
b0 '
b10 $
b0 #
b0 "
b0 !
#1290000
b1 %
b1 '
b1 !
#1300000
b10 %
b10 '
b10 !
#1310000
b11 %
b11 '
b11 !
#1320000
b0 %
b0 '
b1 "
b0 !
#1330000
b1 %
b1 '
b1 !
#1340000
b10 %
b10 '
b10 !
#1350000
b11 %
b11 '
b11 !
#1360000
b0 %
b0 '
b10 "
b0 !
#1370000
b1 %
b1 '
b1 !
#1380000
b10 %
b10 '
b10 !
#1390000
b11 %
b11 '
b11 !
#1400000
b0 %
b0 '
b11 "
b0 !
#1410000
b1 %
b1 '
b1 !
#1420000
b10 %
b10 '
b10 !
#1430000
b11 %
b11 '
b11 !
#1440000
b0 %
b0 '
b1 #
b0 "
b0 !
#1450000
b1 %
b1 '
b1 !
#1460000
b10 %
b10 '
b10 !
#1470000
b11 %
b11 '
b11 !
#1480000
b0 %
b0 '
b1 "
b0 !
#1490000
b1 %
b1 '
b1 !
#1500000
b10 %
b10 '
b10 !
#1510000
b11 %
b11 '
b11 !
#1520000
b0 %
b0 '
b10 "
b0 !
#1530000
b1 %
b1 '
b1 !
#1540000
b10 %
b10 '
b10 !
#1550000
b11 %
b11 '
b11 !
#1560000
b0 %
b0 '
b11 "
b0 !
#1570000
b1 %
b1 '
b1 !
#1580000
b10 %
b10 '
b10 !
#1590000
b11 %
b11 '
b11 !
#1600000
b0 %
b0 '
b10 #
b0 "
b0 !
#1610000
b1 %
b1 '
b1 !
#1620000
b10 %
b10 '
b10 !
#1630000
b11 %
b11 '
b11 !
#1640000
b0 %
b0 '
b1 "
b0 !
#1650000
b1 %
b1 '
b1 !
#1660000
b10 %
b10 '
b10 !
#1670000
b11 %
b11 '
b11 !
#1680000
b0 %
b0 '
b10 "
b0 !
#1690000
b1 %
b1 '
b1 !
#1700000
b10 %
b10 '
b10 !
#1710000
b11 %
b11 '
b11 !
#1720000
b0 %
b0 '
b11 "
b0 !
#1730000
b1 %
b1 '
b1 !
#1740000
b10 %
b10 '
b10 !
#1750000
b11 %
b11 '
b11 !
#1760000
b0 %
b0 '
b11 #
b0 "
b0 !
#1770000
b1 %
b1 '
b1 !
#1780000
b10 %
b10 '
b10 !
#1790000
b11 %
b11 '
b11 !
#1800000
b0 %
b0 '
b1 "
b0 !
#1810000
b1 %
b1 '
b1 !
#1820000
b10 %
b10 '
b10 !
#1830000
b11 %
b11 '
b11 !
#1840000
b0 %
b0 '
b10 "
b0 !
#1850000
b1 %
b1 '
b1 !
#1860000
b10 %
b10 '
b10 !
#1870000
b11 %
b11 '
b11 !
#1880000
b0 %
b0 '
b11 "
b0 !
#1890000
b1 %
b1 '
b1 !
#1900000
b10 %
b10 '
b10 !
#1910000
b11 %
b11 '
b11 !
#1920000
b0 %
b0 '
b11 $
b0 #
b0 "
b0 !
#1930000
b1 %
b1 '
b1 !
#1940000
b10 %
b10 '
b10 !
#1950000
b11 %
b11 '
b11 !
#1960000
b0 %
b0 '
b1 "
b0 !
#1970000
b1 %
b1 '
b1 !
#1980000
b10 %
b10 '
b10 !
#1990000
b11 %
b11 '
b11 !
#2000000
b0 %
b0 '
b10 "
b0 !
#2010000
b1 %
b1 '
b1 !
#2020000
b10 %
b10 '
b10 !
#2030000
b11 %
b11 '
b11 !
#2040000
b0 %
b0 '
b11 "
b0 !
#2050000
b1 %
b1 '
b1 !
#2060000
b10 %
b10 '
b10 !
#2070000
b11 %
b11 '
b11 !
#2080000
b0 %
b0 '
b1 #
b0 "
b0 !
#2090000
b1 %
b1 '
b1 !
#2100000
b10 %
b10 '
b10 !
#2110000
b11 %
b11 '
b11 !
#2120000
b0 %
b0 '
b1 "
b0 !
#2130000
b1 %
b1 '
b1 !
#2140000
b10 %
b10 '
b10 !
#2150000
b11 %
b11 '
b11 !
#2160000
b0 %
b0 '
b10 "
b0 !
#2170000
b1 %
b1 '
b1 !
#2180000
b10 %
b10 '
b10 !
#2190000
b11 %
b11 '
b11 !
#2200000
b0 %
b0 '
b11 "
b0 !
#2210000
b1 %
b1 '
b1 !
#2220000
b10 %
b10 '
b10 !
#2230000
b11 %
b11 '
b11 !
#2240000
b0 %
b0 '
b10 #
b0 "
b0 !
#2250000
b1 %
b1 '
b1 !
#2260000
b10 %
b10 '
b10 !
#2270000
b11 %
b11 '
b11 !
#2280000
b0 %
b0 '
b1 "
b0 !
#2290000
b1 %
b1 '
b1 !
#2300000
b10 %
b10 '
b10 !
#2310000
b11 %
b11 '
b11 !
#2320000
b0 %
b0 '
b10 "
b0 !
#2330000
b1 %
b1 '
b1 !
#2340000
b10 %
b10 '
b10 !
#2350000
b11 %
b11 '
b11 !
#2360000
b0 %
b0 '
b11 "
b0 !
#2370000
b1 %
b1 '
b1 !
#2380000
b10 %
b10 '
b10 !
#2390000
b11 %
b11 '
b11 !
#2400000
b0 %
b0 '
b11 #
b0 "
b0 !
#2410000
b1 %
b1 '
b1 !
#2420000
b10 %
b10 '
b10 !
#2430000
b11 %
b11 '
b11 !
#2440000
b0 %
b0 '
b1 "
b0 !
#2450000
b1 %
b1 '
b1 !
#2460000
b10 %
b10 '
b10 !
#2470000
b11 %
b11 '
b11 !
#2480000
b0 %
b0 '
b10 "
b0 !
#2490000
b1 %
b1 '
b1 !
#2500000
b10 %
b10 '
b10 !
#2510000
b11 %
b11 '
b11 !
#2520000
b0 %
b0 '
b11 "
b0 !
#2530000
b1 %
b1 '
b1 !
#2540000
b10 %
b10 '
b10 !
#2550000
b11 %
b11 '
b11 !
#2560000
b0 %
b0 '
b0 $
b0 #
b0 "
b0 !
b1 &
#2570000
b1 !
#2580000
b10 !
#2590000
b11 !
#2600000
b1 %
b1 '
b1 "
b0 !
#2610000
b1 !
#2620000
b10 !
#2630000
b11 !
#2640000
b10 %
b10 '
b10 "
b0 !
#2650000
b1 !
#2660000
b10 !
#2670000
b11 !
#2680000
b11 %
b11 '
b11 "
b0 !
#2690000
b1 !
#2700000
b10 !
#2710000
b11 !
#2720000
b0 %
b0 '
b1 #
b0 "
b0 !
#2730000
b1 !
#2740000
b10 !
#2750000
b11 !
#2760000
b1 %
b1 '
b1 "
b0 !
#2770000
b1 !
#2780000
b10 !
#2790000
b11 !
#2800000
b10 %
b10 '
b10 "
b0 !
#2810000
b1 !
#2820000
b10 !
#2830000
b11 !
#2840000
b11 %
b11 '
b11 "
b0 !
#2850000
b1 !
#2860000
b10 !
#2870000
b11 !
#2880000
b0 %
b0 '
b10 #
b0 "
b0 !
#2890000
b1 !
#2900000
b10 !
#2910000
b11 !
#2920000
b1 %
b1 '
b1 "
b0 !
#2930000
b1 !
#2940000
b10 !
#2950000
b11 !
#2960000
b10 %
b10 '
b10 "
b0 !
#2970000
b1 !
#2980000
b10 !
#2990000
b11 !
#3000000
b11 %
b11 '
b11 "
b0 !
#3010000
b1 !
#3020000
b10 !
#3030000
b11 !
#3040000
b0 %
b0 '
b11 #
b0 "
b0 !
#3050000
b1 !
#3060000
b10 !
#3070000
b11 !
#3080000
b1 %
b1 '
b1 "
b0 !
#3090000
b1 !
#3100000
b10 !
#3110000
b11 !
#3120000
b10 %
b10 '
b10 "
b0 !
#3130000
b1 !
#3140000
b10 !
#3150000
b11 !
#3160000
b11 %
b11 '
b11 "
b0 !
#3170000
b1 !
#3180000
b10 !
#3190000
b11 !
#3200000
b0 %
b0 '
b1 $
b0 #
b0 "
b0 !
#3210000
b1 !
#3220000
b10 !
#3230000
b11 !
#3240000
b1 %
b1 '
b1 "
b0 !
#3250000
b1 !
#3260000
b10 !
#3270000
b11 !
#3280000
b10 %
b10 '
b10 "
b0 !
#3290000
b1 !
#3300000
b10 !
#3310000
b11 !
#3320000
b11 %
b11 '
b11 "
b0 !
#3330000
b1 !
#3340000
b10 !
#3350000
b11 !
#3360000
b0 %
b0 '
b1 #
b0 "
b0 !
#3370000
b1 !
#3380000
b10 !
#3390000
b11 !
#3400000
b1 %
b1 '
b1 "
b0 !
#3410000
b1 !
#3420000
b10 !
#3430000
b11 !
#3440000
b10 %
b10 '
b10 "
b0 !
#3450000
b1 !
#3460000
b10 !
#3470000
b11 !
#3480000
b11 %
b11 '
b11 "
b0 !
#3490000
b1 !
#3500000
b10 !
#3510000
b11 !
#3520000
b0 %
b0 '
b10 #
b0 "
b0 !
#3530000
b1 !
#3540000
b10 !
#3550000
b11 !
#3560000
b1 %
b1 '
b1 "
b0 !
#3570000
b1 !
#3580000
b10 !
#3590000
b11 !
#3600000
b10 %
b10 '
b10 "
b0 !
#3610000
b1 !
#3620000
b10 !
#3630000
b11 !
#3640000
b11 %
b11 '
b11 "
b0 !
#3650000
b1 !
#3660000
b10 !
#3670000
b11 !
#3680000
b0 %
b0 '
b11 #
b0 "
b0 !
#3690000
b1 !
#3700000
b10 !
#3710000
b11 !
#3720000
b1 %
b1 '
b1 "
b0 !
#3730000
b1 !
#3740000
b10 !
#3750000
b11 !
#3760000
b10 %
b10 '
b10 "
b0 !
#3770000
b1 !
#3780000
b10 !
#3790000
b11 !
#3800000
b11 %
b11 '
b11 "
b0 !
#3810000
b1 !
#3820000
b10 !
#3830000
b11 !
#3840000
b0 %
b0 '
b10 $
b0 #
b0 "
b0 !
#3850000
b1 !
#3860000
b10 !
#3870000
b11 !
#3880000
b1 %
b1 '
b1 "
b0 !
#3890000
b1 !
#3900000
b10 !
#3910000
b11 !
#3920000
b10 %
b10 '
b10 "
b0 !
#3930000
b1 !
#3940000
b10 !
#3950000
b11 !
#3960000
b11 %
b11 '
b11 "
b0 !
#3970000
b1 !
#3980000
b10 !
#3990000
b11 !
#4000000
b0 %
b0 '
b1 #
b0 "
b0 !
#4010000
b1 !
#4020000
b10 !
#4030000
b11 !
#4040000
b1 %
b1 '
b1 "
b0 !
#4050000
b1 !
#4060000
b10 !
#4070000
b11 !
#4080000
b10 %
b10 '
b10 "
b0 !
#4090000
b1 !
#4100000
b10 !
#4110000
b11 !
#4120000
b11 %
b11 '
b11 "
b0 !
#4130000
b1 !
#4140000
b10 !
#4150000
b11 !
#4160000
b0 %
b0 '
b10 #
b0 "
b0 !
#4170000
b1 !
#4180000
b10 !
#4190000
b11 !
#4200000
b1 %
b1 '
b1 "
b0 !
#4210000
b1 !
#4220000
b10 !
#4230000
b11 !
#4240000
b10 %
b10 '
b10 "
b0 !
#4250000
b1 !
#4260000
b10 !
#4270000
b11 !
#4280000
b11 %
b11 '
b11 "
b0 !
#4290000
b1 !
#4300000
b10 !
#4310000
b11 !
#4320000
b0 %
b0 '
b11 #
b0 "
b0 !
#4330000
b1 !
#4340000
b10 !
#4350000
b11 !
#4360000
b1 %
b1 '
b1 "
b0 !
#4370000
b1 !
#4380000
b10 !
#4390000
b11 !
#4400000
b10 %
b10 '
b10 "
b0 !
#4410000
b1 !
#4420000
b10 !
#4430000
b11 !
#4440000
b11 %
b11 '
b11 "
b0 !
#4450000
b1 !
#4460000
b10 !
#4470000
b11 !
#4480000
b0 %
b0 '
b11 $
b0 #
b0 "
b0 !
#4490000
b1 !
#4500000
b10 !
#4510000
b11 !
#4520000
b1 %
b1 '
b1 "
b0 !
#4530000
b1 !
#4540000
b10 !
#4550000
b11 !
#4560000
b10 %
b10 '
b10 "
b0 !
#4570000
b1 !
#4580000
b10 !
#4590000
b11 !
#4600000
b11 %
b11 '
b11 "
b0 !
#4610000
b1 !
#4620000
b10 !
#4630000
b11 !
#4640000
b0 %
b0 '
b1 #
b0 "
b0 !
#4650000
b1 !
#4660000
b10 !
#4670000
b11 !
#4680000
b1 %
b1 '
b1 "
b0 !
#4690000
b1 !
#4700000
b10 !
#4710000
b11 !
#4720000
b10 %
b10 '
b10 "
b0 !
#4730000
b1 !
#4740000
b10 !
#4750000
b11 !
#4760000
b11 %
b11 '
b11 "
b0 !
#4770000
b1 !
#4780000
b10 !
#4790000
b11 !
#4800000
b0 %
b0 '
b10 #
b0 "
b0 !
#4810000
b1 !
#4820000
b10 !
#4830000
b11 !
#4840000
b1 %
b1 '
b1 "
b0 !
#4850000
b1 !
#4860000
b10 !
#4870000
b11 !
#4880000
b10 %
b10 '
b10 "
b0 !
#4890000
b1 !
#4900000
b10 !
#4910000
b11 !
#4920000
b11 %
b11 '
b11 "
b0 !
#4930000
b1 !
#4940000
b10 !
#4950000
b11 !
#4960000
b0 %
b0 '
b11 #
b0 "
b0 !
#4970000
b1 !
#4980000
b10 !
#4990000
b11 !
#5000000
b1 %
b1 '
b1 "
b0 !
#5010000
b1 !
#5020000
b10 !
#5030000
b11 !
#5040000
b10 %
b10 '
b10 "
b0 !
#5050000
b1 !
#5060000
b10 !
#5070000
b11 !
#5080000
b11 %
b11 '
b11 "
b0 !
#5090000
b1 !
#5100000
b10 !
#5110000
b11 !
#5120000
b0 %
b0 '
b0 $
b0 #
b0 "
b0 !
b10 &
#5130000
b1 !
#5140000
b10 !
#5150000
b11 !
#5160000
b1 "
b0 !
#5170000
b1 !
#5180000
b10 !
#5190000
b11 !
#5200000
b10 "
b0 !
#5210000
b1 !
#5220000
b10 !
#5230000
b11 !
#5240000
b11 "
b0 !
#5250000
b1 !
#5260000
b10 !
#5270000
b11 !
#5280000
b1 %
b1 '
b1 #
b0 "
b0 !
#5290000
b1 !
#5300000
b10 !
#5310000
b11 !
#5320000
b1 "
b0 !
#5330000
b1 !
#5340000
b10 !
#5350000
b11 !
#5360000
b10 "
b0 !
#5370000
b1 !
#5380000
b10 !
#5390000
b11 !
#5400000
b11 "
b0 !
#5410000
b1 !
#5420000
b10 !
#5430000
b11 !
#5440000
b10 %
b10 '
b10 #
b0 "
b0 !
#5450000
b1 !
#5460000
b10 !
#5470000
b11 !
#5480000
b1 "
b0 !
#5490000
b1 !
#5500000
b10 !
#5510000
b11 !
#5520000
b10 "
b0 !
#5530000
b1 !
#5540000
b10 !
#5550000
b11 !
#5560000
b11 "
b0 !
#5570000
b1 !
#5580000
b10 !
#5590000
b11 !
#5600000
b11 %
b11 '
b11 #
b0 "
b0 !
#5610000
b1 !
#5620000
b10 !
#5630000
b11 !
#5640000
b1 "
b0 !
#5650000
b1 !
#5660000
b10 !
#5670000
b11 !
#5680000
b10 "
b0 !
#5690000
b1 !
#5700000
b10 !
#5710000
b11 !
#5720000
b11 "
b0 !
#5730000
b1 !
#5740000
b10 !
#5750000
b11 !
#5760000
b0 %
b0 '
b1 $
b0 #
b0 "
b0 !
#5770000
b1 !
#5780000
b10 !
#5790000
b11 !
#5800000
b1 "
b0 !
#5810000
b1 !
#5820000
b10 !
#5830000
b11 !
#5840000
b10 "
b0 !
#5850000
b1 !
#5860000
b10 !
#5870000
b11 !
#5880000
b11 "
b0 !
#5890000
b1 !
#5900000
b10 !
#5910000
b11 !
#5920000
b1 %
b1 '
b1 #
b0 "
b0 !
#5930000
b1 !
#5940000
b10 !
#5950000
b11 !
#5960000
b1 "
b0 !
#5970000
b1 !
#5980000
b10 !
#5990000
b11 !
#6000000
b10 "
b0 !
#6010000
b1 !
#6020000
b10 !
#6030000
b11 !
#6040000
b11 "
b0 !
#6050000
b1 !
#6060000
b10 !
#6070000
b11 !
#6080000
b10 %
b10 '
b10 #
b0 "
b0 !
#6090000
b1 !
#6100000
b10 !
#6110000
b11 !
#6120000
b1 "
b0 !
#6130000
b1 !
#6140000
b10 !
#6150000
b11 !
#6160000
b10 "
b0 !
#6170000
b1 !
#6180000
b10 !
#6190000
b11 !
#6200000
b11 "
b0 !
#6210000
b1 !
#6220000
b10 !
#6230000
b11 !
#6240000
b11 %
b11 '
b11 #
b0 "
b0 !
#6250000
b1 !
#6260000
b10 !
#6270000
b11 !
#6280000
b1 "
b0 !
#6290000
b1 !
#6300000
b10 !
#6310000
b11 !
#6320000
b10 "
b0 !
#6330000
b1 !
#6340000
b10 !
#6350000
b11 !
#6360000
b11 "
b0 !
#6370000
b1 !
#6380000
b10 !
#6390000
b11 !
#6400000
b0 %
b0 '
b10 $
b0 #
b0 "
b0 !
#6410000
b1 !
#6420000
b10 !
#6430000
b11 !
#6440000
b1 "
b0 !
#6450000
b1 !
#6460000
b10 !
#6470000
b11 !
#6480000
b10 "
b0 !
#6490000
b1 !
#6500000
b10 !
#6510000
b11 !
#6520000
b11 "
b0 !
#6530000
b1 !
#6540000
b10 !
#6550000
b11 !
#6560000
b1 %
b1 '
b1 #
b0 "
b0 !
#6570000
b1 !
#6580000
b10 !
#6590000
b11 !
#6600000
b1 "
b0 !
#6610000
b1 !
#6620000
b10 !
#6630000
b11 !
#6640000
b10 "
b0 !
#6650000
b1 !
#6660000
b10 !
#6670000
b11 !
#6680000
b11 "
b0 !
#6690000
b1 !
#6700000
b10 !
#6710000
b11 !
#6720000
b10 %
b10 '
b10 #
b0 "
b0 !
#6730000
b1 !
#6740000
b10 !
#6750000
b11 !
#6760000
b1 "
b0 !
#6770000
b1 !
#6780000
b10 !
#6790000
b11 !
#6800000
b10 "
b0 !
#6810000
b1 !
#6820000
b10 !
#6830000
b11 !
#6840000
b11 "
b0 !
#6850000
b1 !
#6860000
b10 !
#6870000
b11 !
#6880000
b11 %
b11 '
b11 #
b0 "
b0 !
#6890000
b1 !
#6900000
b10 !
#6910000
b11 !
#6920000
b1 "
b0 !
#6930000
b1 !
#6940000
b10 !
#6950000
b11 !
#6960000
b10 "
b0 !
#6970000
b1 !
#6980000
b10 !
#6990000
b11 !
#7000000
b11 "
b0 !
#7010000
b1 !
#7020000
b10 !
#7030000
b11 !
#7040000
b0 %
b0 '
b11 $
b0 #
b0 "
b0 !
#7050000
b1 !
#7060000
b10 !
#7070000
b11 !
#7080000
b1 "
b0 !
#7090000
b1 !
#7100000
b10 !
#7110000
b11 !
#7120000
b10 "
b0 !
#7130000
b1 !
#7140000
b10 !
#7150000
b11 !
#7160000
b11 "
b0 !
#7170000
b1 !
#7180000
b10 !
#7190000
b11 !
#7200000
b1 %
b1 '
b1 #
b0 "
b0 !
#7210000
b1 !
#7220000
b10 !
#7230000
b11 !
#7240000
b1 "
b0 !
#7250000
b1 !
#7260000
b10 !
#7270000
b11 !
#7280000
b10 "
b0 !
#7290000
b1 !
#7300000
b10 !
#7310000
b11 !
#7320000
b11 "
b0 !
#7330000
b1 !
#7340000
b10 !
#7350000
b11 !
#7360000
b10 %
b10 '
b10 #
b0 "
b0 !
#7370000
b1 !
#7380000
b10 !
#7390000
b11 !
#7400000
b1 "
b0 !
#7410000
b1 !
#7420000
b10 !
#7430000
b11 !
#7440000
b10 "
b0 !
#7450000
b1 !
#7460000
b10 !
#7470000
b11 !
#7480000
b11 "
b0 !
#7490000
b1 !
#7500000
b10 !
#7510000
b11 !
#7520000
b11 %
b11 '
b11 #
b0 "
b0 !
#7530000
b1 !
#7540000
b10 !
#7550000
b11 !
#7560000
b1 "
b0 !
#7570000
b1 !
#7580000
b10 !
#7590000
b11 !
#7600000
b10 "
b0 !
#7610000
b1 !
#7620000
b10 !
#7630000
b11 !
#7640000
b11 "
b0 !
#7650000
b1 !
#7660000
b10 !
#7670000
b11 !
#7680000
b0 %
b0 '
b0 $
b0 #
b0 "
b0 !
b11 &
#7690000
b1 !
#7700000
b10 !
#7710000
b11 !
#7720000
b1 "
b0 !
#7730000
b1 !
#7740000
b10 !
#7750000
b11 !
#7760000
b10 "
b0 !
#7770000
b1 !
#7780000
b10 !
#7790000
b11 !
#7800000
b11 "
b0 !
#7810000
b1 !
#7820000
b10 !
#7830000
b11 !
#7840000
b1 #
b0 "
b0 !
#7850000
b1 !
#7860000
b10 !
#7870000
b11 !
#7880000
b1 "
b0 !
#7890000
b1 !
#7900000
b10 !
#7910000
b11 !
#7920000
b10 "
b0 !
#7930000
b1 !
#7940000
b10 !
#7950000
b11 !
#7960000
b11 "
b0 !
#7970000
b1 !
#7980000
b10 !
#7990000
b11 !
#8000000
b10 #
b0 "
b0 !
#8010000
b1 !
#8020000
b10 !
#8030000
b11 !
#8040000
b1 "
b0 !
#8050000
b1 !
#8060000
b10 !
#8070000
b11 !
#8080000
b10 "
b0 !
#8090000
b1 !
#8100000
b10 !
#8110000
b11 !
#8120000
b11 "
b0 !
#8130000
b1 !
#8140000
b10 !
#8150000
b11 !
#8160000
b11 #
b0 "
b0 !
#8170000
b1 !
#8180000
b10 !
#8190000
b11 !
#8200000
b1 "
b0 !
#8210000
b1 !
#8220000
b10 !
#8230000
b11 !
#8240000
b10 "
b0 !
#8250000
b1 !
#8260000
b10 !
#8270000
b11 !
#8280000
b11 "
b0 !
#8290000
b1 !
#8300000
b10 !
#8310000
b11 !
#8320000
b1 %
b1 '
b1 $
b0 #
b0 "
b0 !
#8330000
b1 !
#8340000
b10 !
#8350000
b11 !
#8360000
b1 "
b0 !
#8370000
b1 !
#8380000
b10 !
#8390000
b11 !
#8400000
b10 "
b0 !
#8410000
b1 !
#8420000
b10 !
#8430000
b11 !
#8440000
b11 "
b0 !
#8450000
b1 !
#8460000
b10 !
#8470000
b11 !
#8480000
b1 #
b0 "
b0 !
#8490000
b1 !
#8500000
b10 !
#8510000
b11 !
#8520000
b1 "
b0 !
#8530000
b1 !
#8540000
b10 !
#8550000
b11 !
#8560000
b10 "
b0 !
#8570000
b1 !
#8580000
b10 !
#8590000
b11 !
#8600000
b11 "
b0 !
#8610000
b1 !
#8620000
b10 !
#8630000
b11 !
#8640000
b10 #
b0 "
b0 !
#8650000
b1 !
#8660000
b10 !
#8670000
b11 !
#8680000
b1 "
b0 !
#8690000
b1 !
#8700000
b10 !
#8710000
b11 !
#8720000
b10 "
b0 !
#8730000
b1 !
#8740000
b10 !
#8750000
b11 !
#8760000
b11 "
b0 !
#8770000
b1 !
#8780000
b10 !
#8790000
b11 !
#8800000
b11 #
b0 "
b0 !
#8810000
b1 !
#8820000
b10 !
#8830000
b11 !
#8840000
b1 "
b0 !
#8850000
b1 !
#8860000
b10 !
#8870000
b11 !
#8880000
b10 "
b0 !
#8890000
b1 !
#8900000
b10 !
#8910000
b11 !
#8920000
b11 "
b0 !
#8930000
b1 !
#8940000
b10 !
#8950000
b11 !
#8960000
b10 %
b10 '
b10 $
b0 #
b0 "
b0 !
#8970000
b1 !
#8980000
b10 !
#8990000
b11 !
#9000000
b1 "
b0 !
#9010000
b1 !
#9020000
b10 !
#9030000
b11 !
#9040000
b10 "
b0 !
#9050000
b1 !
#9060000
b10 !
#9070000
b11 !
#9080000
b11 "
b0 !
