project3_Combinational Logic Circuits/02five_way.v
module five_way(input [4:0] sw, output  led); //ABCDE

assign led = sw[0]&{(sw[4]^sw[3])&(sw[2]^sw[1])|(~(sw[4]^sw[3])& ~(sw[2]^sw[1]))}|
            ~sw[0]&~{(sw[4]^sw[3])&(sw[2]^sw[1])|(~(sw[4]^sw[3])& ~(sw[2]^sw[1]))} ;




endmodule

project3_Combinational Logic Circuits/five_way_tb.v
`timescale 1 ns / 100 ps
module five_way_tb();
reg [4:0]sw;
wire led;
five_way name(.sw(sw),.led(led));
initial 
 begin
    $dumpfile("five_way.vcd");
    $dumpvars(0,name);
    #0 sw = 5'b00000;
    #2 sw = 5'b10000;
    #2 sw = 5'b10100;
    #2 sw = 5'b00100;
    #2 sw = 5'b01100;
    #2 sw = 5'b01101;
    #2 sw = 5'b00101;
    #2 sw = 5'b11001;
    #10 $finish;

 end    
endmodule

project3_Combinational Logic Circuits/five_way.vcd
$date
	Sun Mar 27 22:28:33 2022
$end
$version
	Icarus Verilog
$end
$timescale
	100ps
$end
$scope module five_way_tb $end
$scope module name $end
$var wire 1 ! led $end
$var wire 5 " sw [4:0] $end
$upscope $end
$upscope $end
$enddefinitions $end
#0
$dumpvars
b0 "
0!
$end
#20
1!
b10000 "
#40
0!
b10100 "
#60
1!
b100 "
#80
0!
b1100 "
#100
1!
b1101 "
#120
0!
b101 "
#140
1!
b11001 "
