project3_Combinational Logic Circuits/odd_even.v
module odd_even(input [7:0]sw, output [1:0]led); //odd even
  
assign led[0] = ((sw[7]^sw[6])^(sw[5]^sw[4]))^((sw[3]^sw[2])^(sw[1]^sw[0]));
assign led[1] = ~(((sw[7]^sw[6])^(sw[5]^sw[4]))^((sw[3]^sw[2])^(sw[1]^sw[0])));

endmodule

project3_Combinational Logic Circuits/odd_even_tb.v
`timescale 1ps/1ps
module odd_even_tb();
reg [7:0]sw;
wire [1:0]led;
odd_even name(.sw(sw),.led(led));
initial 
 begin
    $dumpfile("odd_even.vcd");
    $dumpvars(0,name);
    #0 sw = 8'b00000000;
    #2 sw = 8'b01100000;
    #2 sw = 8'b00011100;
    #2 sw = 8'b01010101;
    #2 sw = 8'b01011110;
    #2 sw = 8'b01111011;
    #2 sw = 8'b10111111;
    #2 sw = 8'b11111111;
    #10 $finish;

 end    
endmodule

project3_Combinational Logic Circuits/odd_even.vcd
$date
	Mon Mar 28 16:20:38 2022
$end
$version
	Icarus Verilog
$end
$timescale
	1ps
$end
$scope module odd_even_tb $end
$scope module name $end
$var wire 8 ! sw [7:0] $end
$var wire 2 " led [1:0] $end
$upscope $end
$upscope $end
$enddefinitions $end
#0
$dumpvars
b10 "
b0 !
$end
#2
b1100000 !
#4
b1 "
b11100 !
#6
b10 "
b1010101 !
#8
b1 "
b1011110 !
#10
b10 "
b1111011 !
#12
b1 "
b10111111 !
#14
b10 "
b11111111 !
