project3_Combinational Logic Circuits/03temp.v
module temp(input [7:0] sw, output  led); //ABCDE

// reg led
// always @(sw)
// begin
//  if (sw >= 8'd161 && sw <= 8'd185)
//     led = 1;
//  else
//     led = 0;   
// end
assign led = (sw[7] & ~sw[6] & sw[5] & ~sw[4])&(sw[3]|sw[2]|sw[1]|sw[0])|
             (sw[7] & ~sw[6] & sw[5] & sw[4])&(~sw[3]| (sw[3]&~sw[2]&~sw[1]));

endmodule

project3_Combinational Logic Circuits/temp_tb.v
`timescale 1 ns / 100 ps
module temp_tb();
reg [7:0]sw;
wire led;
temp name(.sw(sw),.led(led));
initial 
 begin
    $dumpfile("temp.vcd");
    $dumpvars(0,name);
    #0 sw = 8'd0;
    #2 sw = 8'd10;
    #2 sw = 8'd160;
    #2 sw = 8'd161;
    #2 sw = 8'd186;
    #2 sw = 8'd185;
    #2 sw = 8'd200;
    #2 sw = 8'd170;
    #10 $finish;

 end    
endmodule

project3_Combinational Logic Circuits/temp.vcd
$date
	Mon Mar 28 12:05:24 2022
$end
$version
	Icarus Verilog
$end
$timescale
	100ps
$end
$scope module temp_tb $end
$scope module name $end
$var wire 1 ! led $end
$var wire 8 " sw [7:0] $end
$upscope $end
$upscope $end
$enddefinitions $end
#0
$dumpvars
b0 "
0!
$end
#20
b1010 "
#40
b10100000 "
#60
1!
b10100001 "
#80
0!
b10111010 "
#100
1!
b10111001 "
#120
0!
b11001000 "
#140
1!
b10101010 "
