project2_Basic Logic Circuits/auto_con.v
module auto_con(
    input ct,cl ,ot,ol,// ct cl ot ol
    output [1:0] RGB // RGB[0] = blue, RGB[1] = red
);
assign RGB[0] = (ct & (ot | ol))|
                (ot & ~ol)|
                (~ct & cl & ~ot & ~ol)|
                (~ct & ~cl & ~ot & ol);
assign RGB[1] = (ct & cl )| (ot & ol)| (ct & ot)   ;             

endmodule

project2_Basic Logic Circuits/auto_con_tb.v
`timescale 1 ns / 100 ps

module auto_con_tb;
 reg [3:0] sensor;
 wire [2:0] RGB;
 auto_con name(.ct(sensor[0]),
          .cl(sensor[1]),
          .ot(sensor[2]),
          .ol(sensor[3]));
initial 
 begin
    $dumpfile("auto_con.vcd");
    $dumpvars(0,name);
    #0  sensor = 4'd0;
    #2 sensor = 4'd1;
    #2 sensor = 4'd2;
    #2 sensor = 4'd3;
    #2 sensor = 4'd4;
    #2 sensor = 4'd5;
    #2 sensor = 4'd6;
    #2 sensor = 4'd7;
    #2 sensor = 4'd8;
    #2 sensor = 4'd9;
    #2 sensor = 4'd10;
    #2 sensor = 4'd11;
    #2 sensor = 4'd12;
    #2 sensor = 4'd13;

    #10 $finish;

 end    


endmodule

project2_Basic Logic Circuits/auto_con.vcd
$date
	Thu Mar 24 15:12:38 2022
$end
$version
	Icarus Verilog
$end
$timescale
	100ps
$end
$scope module auto_con_tb $end
$scope module name $end
$var wire 1 ! cl $end
$var wire 1 " ct $end
$var wire 1 # ol $end
$var wire 1 $ ot $end
$var wire 2 % RGB [1:0] $end
$upscope $end
$upscope $end
$enddefinitions $end
#0
$dumpvars
b0 %
0$
0#
0"
0!
$end
#20
1"
#40
b1 %
0"
1!
#60
b10 %
1"
#80
b1 %
0"
0!
1$
#100
b11 %
1"
#120
b1 %
0"
1!
#140
b11 %
1"
#160
b1 %
0"
0!
0$
1#
#180
1"
#200
b0 %
0"
1!
#220
b11 %
1"
#240
b10 %
0"
0!
1$
#260
b11 %
1"
