project7_Flip-flops and Latches/05PISO.v
module PISO_shift_register(
input [7:0] sw,
input [1:0]btn,
input clk,
output reg[15:0]led
);
////////clk_div///////////
reg [25:0] cnt = 0;
reg clk_div =1 ;
parameter CLK_DIVDER = 5;
always @(posedge clk)begin
    if (cnt==CLK_DIVDER-1) cnt <=0;
    else cnt <= cnt+1;
end
always @(posedge clk)begin
   if(cnt==CLK_DIVDER-1) clk_div <= ~clk_div;
   else  clk_div <= clk_div;
end
/////////////////////////
////////PISO//////////
reg[7:0] Q;
always @(posedge clk_div)begin
    if(btn[0]) led[7:0]<=sw;
    else led <= {led[14:0],1'b0};
end

always @(posedge clk_div)begin
    if(btn[1]) led[15:8]<= sw;
    else led <= {led[14:0],1'b0};
end


endmodule

project7_Flip-flops and Latches/05test.v
`timescale 1ns / 1ps
module test_tb;
reg [7:0] sw;
reg [1:0]btn;
reg clk;
wire[15:0]led;
PISO_shift_register name(sw,btn,clk,led);

always #1 clk = ~clk;

initial begin
    $dumpfile("05test.vcd");
    $dumpvars;
    clk = 0;
    sw = 8'b01010011;
    #30 btn = 2'b11;
    #20 btn = 2'b00;
    
  
    #100 ;
    $finish;
end
    endmodule

project7_Flip-flops and Latches/05test.vcd
$date
	Wed May 11 23:38:15 2022
$end
$version
	Icarus Verilog
$end
$timescale
	1ps
$end
$scope module test_tb $end
$var wire 16 ! led [15:0] $end
$var reg 2 " btn [1:0] $end
$var reg 1 # clk $end
$var reg 8 $ sw [7:0] $end
$scope module name $end
$var wire 2 % btn [1:0] $end
$var wire 1 # clk $end
$var wire 8 & sw [7:0] $end
$var reg 1 ' clk_div $end
$var reg 26 ( cnt [25:0] $end
$var reg 16 ) led [15:0] $end
$upscope $end
$upscope $end
$enddefinitions $end
#0
$dumpvars
bx )
b0 (
1'
b1010011 &
bx %
b1010011 $
0#
bx "
bx !
$end
#1000
b1 (
1#
#2000
0#
#3000
b10 (
1#
#4000
0#
#5000
b11 (
1#
#6000
0#
#7000
b100 (
1#
#8000
0#
#9000
b0 (
0'
1#
#10000
0#
#11000
b1 (
1#
#12000
0#
#13000
b10 (
1#
#14000
0#
#15000
b11 (
1#
#16000
0#
#17000
b100 (
1#
#18000
0#
#19000
bx0 !
bx0 )
1'
b0 (
1#
#20000
0#
#21000
b1 (
1#
#22000
0#
#23000
b10 (
1#
#24000
0#
#25000
b11 (
1#
#26000
0#
#27000
b100 (
1#
#28000
0#
#29000
b0 (
0'
1#
#30000
0#
b11 "
b11 %
#31000
b1 (
1#
#32000
0#
#33000
b10 (
1#
#34000
0#
#35000
b11 (
1#
#36000
0#
#37000
b100 (
1#
#38000
0#
#39000
b101001101010011 !
b101001101010011 )
1'
b0 (
1#
#40000
0#
#41000
b1 (
1#
#42000
0#
#43000
b10 (
1#
#44000
0#
#45000
b11 (
1#
#46000
0#
#47000
b100 (
1#
#48000
0#
#49000
b0 (
0'
1#
#50000
0#
b0 "
b0 %
#51000
b1 (
1#
#52000
0#
#53000
b10 (
1#
#54000
0#
#55000
b11 (
1#
#56000
0#
#57000
b100 (
1#
#58000
0#
#59000
b1010011010100110 !
b1010011010100110 )
1'
b0 (
1#
#60000
0#
#61000
b1 (
1#
#62000
0#
#63000
b10 (
1#
#64000
0#
#65000
b11 (
1#
#66000
0#
#67000
b100 (
1#
#68000
0#
#69000
b0 (
0'
1#
#70000
0#
#71000
b1 (
1#
#72000
0#
#73000
b10 (
1#
#74000
0#
#75000
b11 (
1#
#76000
0#
#77000
b100 (
1#
#78000
0#
#79000
b100110101001100 !
b100110101001100 )
1'
b0 (
1#
#80000
0#
#81000
b1 (
1#
#82000
0#
#83000
b10 (
1#
#84000
0#
#85000
b11 (
1#
#86000
0#
#87000
b100 (
1#
#88000
0#
#89000
b0 (
0'
1#
#90000
0#
#91000
b1 (
1#
#92000
0#
#93000
b10 (
1#
#94000
0#
#95000
b11 (
1#
#96000
0#
#97000
b100 (
1#
#98000
0#
#99000
b1001101010011000 !
b1001101010011000 )
1'
b0 (
1#
#100000
0#
#101000
b1 (
1#
#102000
0#
#103000
b10 (
1#
#104000
0#
#105000
b11 (
1#
#106000
0#
#107000
b100 (
1#
#108000
0#
#109000
b0 (
0'
1#
#110000
0#
#111000
b1 (
1#
#112000
0#
#113000
b10 (
1#
#114000
0#
#115000
b11 (
1#
#116000
0#
#117000
b100 (
1#
#118000
0#
#119000
b11010100110000 !
b11010100110000 )
1'
b0 (
1#
#120000
0#
#121000
b1 (
1#
#122000
0#
#123000
b10 (
1#
#124000
0#
#125000
b11 (
1#
#126000
0#
#127000
b100 (
1#
#128000
0#
#129000
b0 (
0'
1#
#130000
0#
#131000
b1 (
1#
#132000
0#
#133000
b10 (
1#
#134000
0#
#135000
b11 (
1#
#136000
0#
#137000
b100 (
1#
#138000
0#
#139000
b110101001100000 !
b110101001100000 )
1'
b0 (
1#
#140000
0#
#141000
b1 (
1#
#142000
0#
#143000
b10 (
1#
#144000
0#
#145000
b11 (
1#
#146000
0#
#147000
b100 (
1#
#148000
0#
#149000
b0 (
0'
1#
