project7_Flip-flops and Latches/01SR_latch.v
`timescale 1ns / 1ps
module sr_latch(
    input S,
    input R,
    output Q,
    output Qn
    );

wire Q_int, Qn_int;
//------- NAND basic------------///
// assign #1 Q_int = ~(S & Qn_int);
// assign #1 Qn_int = ~(R & Q_int);
// assign Q = Q_int;
// assign Qn = Qn_int;

//------- NOR basic------------///
assign #1 Qn_int = ~(S | Q_int);
assign #1 Q_int = ~(R | Qn_int);
assign Q = Q_int;
assign Qn = Qn_int;

endmodule

project7_Flip-flops and Latches/SR_latch_tb.v
`timescale 1ns / 1ps
module sr_latch_tb;
   reg S;
   reg R;
   wire Q;
   wire Qn;

sr_latch name(S,R,Q,Qn);

initial begin
    $dumpfile("SR_latch_NOR.vcd");
    $dumpvars;
    // Initialize Inputs
//     S = 1;
//     R = 1;

//     // Add stimulus here NAND
//     #100 S = 0;
//     #100 S = 1;
//     #100 R = 0;
//     #100 R = 1;
//     #100 S = 0;
//          R = 0;
//     #100 S = 1;
//          R = 1;
//     #100 S = 0;
//          R = 0;
//     #100 ;

    // Add stimulus here NOR
     S = 0;
     R = 0;
    #100 S = 1;
    #100 S = 0;
    #100 R = 1;
    #100 R = 0;
    #100 S = 1;
         R = 1;
    #100 S = 0;
         R = 0;
    #100 S = 1;
         R = 1;
    #100 ;
end
endmodule

project7_Flip-flops and Latches/SR_latch_NOR.vcd
$date
	Tue Apr 12 15:11:20 2022
$end
$version
	Icarus Verilog
$end
$timescale
	1ps
$end
$scope module sr_latch_tb $end
$var wire 1 ! Qn $end
$var wire 1 " Q $end
$var reg 1 # R $end
$var reg 1 $ S $end
$scope module name $end
$var wire 1 " Q $end
$var wire 1 % Q_int $end
$var wire 1 ! Qn $end
$var wire 1 & Qn_int $end
$var wire 1 # R $end
$var wire 1 $ S $end
$upscope $end
$upscope $end
$enddefinitions $end
#0
$dumpvars
x&
x%
0$
0#
x"
x!
$end
#100000
1$
#101000
0!
0&
#102000
1"
1%
#200000
0$
#300000
1#
#301000
0"
0%
#302000
1!
1&
#400000
0#
#500000
1#
1$
#501000
0!
0&
#600000
0#
0$
#601000
1"
1%
1!
1&
#602000
0!
0&
0"
0%
#603000
1"
1%
1!
1&
#604000
0!
0&
0"
0%
#605000
1"
1%
1!
1&
#606000
0!
0&
0"
0%
#607000
1"
1%
1!
1&
#608000
0!
0&
0"
0%
#609000
1"
1%
1!
1&
#610000
0!
0&
0"
0%
#611000
1"
1%
1!
1&
#612000
0!
0&
0"
0%
#613000
1"
1%
1!
1&
#614000
0!
0&
0"
0%
#615000
1"
1%
1!
1&
#616000
0!
0&
0"
0%
#617000
1"
1%
1!
1&
#618000
0!
0&
0"
0%
#619000
1"
1%
1!
1&
#620000
0!
0&
0"
0%
#621000
1"
1%
1!
1&
#622000
0!
0&
0"
0%
#623000
1"
1%
1!
1&
#624000
0!
0&
0"
0%
#625000
1"
1%
1!
1&
#626000
0!
0&
0"
0%
#627000
1"
1%
1!
1&
#628000
0!
0&
0"
0%
#629000
1"
1%
1!
1&
#630000
0!
0&
0"
0%
#631000
1"
1%
1!
1&
#632000
0!
0&
0"
0%
#633000
1"
1%
1!
1&
#634000
0!
0&
0"
0%
#635000
1"
1%
1!
1&
#636000
0!
0&
0"
0%
#637000
1"
1%
1!
1&
#638000
0!
0&
0"
0%
#639000
1"
1%
1!
1&
#640000
0!
0&
0"
0%
#641000
1"
1%
1!
1&
#642000
0!
0&
0"
0%
#643000
1"
1%
1!
1&
#644000
0!
0&
0"
0%
#645000
1"
1%
1!
1&
#646000
0!
0&
0"
0%
#647000
1"
1%
1!
1&
#648000
0!
0&
0"
0%
#649000
1"
1%
1!
1&
#650000
0!
0&
0"
0%
#651000
1"
1%
1!
1&
#652000
0!
0&
0"
0%
#653000
1"
1%
1!
1&
#654000
0!
0&
0"
0%
#655000
1"
1%
1!
1&
#656000
0!
0&
0"
0%
#657000
1"
1%
1!
1&
#658000
0!
0&
0"
0%
#659000
1"
1%
1!
1&
#660000
0!
0&
0"
0%
#661000
1"
1%
1!
1&
#662000
0!
0&
0"
0%
#663000
1"
1%
1!
1&
#664000
0!
0&
0"
0%
#665000
1"
1%
1!
1&
#666000
0!
0&
0"
0%
#667000
1"
1%
1!
1&
#668000
0!
0&
0"
0%
#669000
1"
1%
1!
1&
#670000
0!
0&
0"
0%
#671000
1"
1%
1!
1&
#672000
0!
0&
0"
0%
#673000
1"
1%
1!
1&
#674000
0!
0&
0"
0%
#675000
1"
1%
1!
1&
#676000
0!
0&
0"
0%
#677000
1"
1%
1!
1&
#678000
0!
0&
0"
0%
#679000
1"
1%
1!
1&
#680000
0!
0&
0"
0%
#681000
1"
1%
1!
1&
#682000
0!
0&
0"
0%
#683000
1"
1%
1!
1&
#684000
0!
0&
0"
0%
#685000
1"
1%
1!
1&
#686000
0!
0&
0"
0%
#687000
1"
1%
1!
1&
#688000
0!
0&
0"
0%
#689000
1"
1%
1!
1&
#690000
0!
0&
0"
0%
#691000
1"
1%
1!
1&
#692000
0!
0&
0"
0%
#693000
1"
1%
1!
1&
#694000
0!
0&
0"
0%
#695000
1"
1%
1!
1&
#696000
0!
0&
0"
0%
#697000
1"
1%
1!
1&
#698000
0!
0&
0"
0%
#699000
1"
1%
1!
1&
#700000
0!
0&
0"
0%
1#
1$
