project5_Structural Verilog for Combinational Circuits/bin2seg/bin2seg.v
module bin2seg(
    input [3:0] B,
    output reg [6:0] seg7
);
always @(B) begin
 case (B)
   4'h0  :  seg7 <= 7'b1111_110;
   4'h1  :  seg7 <= 7'b0110_000;
   4'h2  :  seg7 <= 7'b1101_101;
   4'h3  :  seg7 <= 7'b1111_001;
   4'h4  :  seg7 <= 7'b0110_011;
   4'h5  :  seg7 <= 7'b1011_011;
   4'h6  :  seg7 <= 7'b1011_111;
   4'h7  :  seg7 <= 7'b1110_000;
   4'h8  :  seg7 <= 7'b1111_111;
   4'h9  :  seg7 <= 7'b1111_011;
   4'hA  :  seg7 <= 7'b1110_111;
   4'hB  :  seg7 <= 7'b0011_111;
   4'hC  :  seg7 <= 7'b1001_110;
   4'hD  :  seg7 <= 7'b0111_101;
   4'hE  :  seg7 <= 7'b1001_111;
   4'hF  :  seg7 <= 7'b1000_111;
   default :  seg7 <= 7'b0000_000;
 endcase
end


endmodule

project5_Structural Verilog for Combinational Circuits/bin2seg/mux2_1.v
module mux2_1(
    input [7:0] sw,
    input sel,
    output reg [3:0] data
);

always @(sw,sel)begin
    case (sel)
     1'b0 : data <= sw[7:4];
     1'b1 : data <= sw[3:0];
     default : data <= 4'b0000;
    endcase
end

endmodule

project5_Structural Verilog for Combinational Circuits/bin2seg/two_7seg.v
module two_7seg(
    input [7:0] sw,
    input btn,
    output [6:0] seg
);  
wire [3:0] sdata;
mux2_1 input_mux(
    .sw(sw),
    .sel(btn),
    .data(sdata)
);

bin2seg output_seg(
    .B(sdata),
    .seg7(seg)
);

endmodule

project5_Structural Verilog for Combinational Circuits/bin2seg/two_7seg_tb.v
module two_7seg_tb;
reg[7:0] sw;
reg btn;
wire [6:0] seg;

two_7seg name(
    .sw(sw),
    .btn(btn),
    .seg(seg)
);

always begin
   #5 btn = ~btn;
end
initial begin
    $dumpfile("two_7seg.vcd");
    $dumpvars(0,name); 
    btn = 0;
    sw = 0;
    #10 sw = 8'b1111_0001 ; //F1
    #10 sw = 8'b1110_0010; // E2
    #10 sw = 8'b1110_0011; // D3
    #10 sw = 8'b1101_0100; // C4
    #10 sw = 8'b1100_0101; // B5
    #10 $stop;
end

 endmodule

project5_Structural Verilog for Combinational Circuits/bin2seg/two_7seg.vcd
$date
	Sat Apr  2 23:04:36 2022
$end
$version
	Icarus Verilog
$end
$timescale
	1s
$end
$scope module two_7seg_tb $end
$scope module name $end
$var wire 1 ! btn $end
$var wire 8 " sw [7:0] $end
$var wire 7 # seg [6:0] $end
$var wire 4 $ sdata [3:0] $end
$scope module input_mux $end
$var wire 1 ! sel $end
$var wire 8 % sw [7:0] $end
$var reg 4 & data [3:0] $end
$upscope $end
$scope module output_seg $end
$var wire 4 ' B [3:0] $end
$var reg 7 ( seg7 [6:0] $end
$upscope $end
$upscope $end
$upscope $end
$enddefinitions $end
#0
$dumpvars
b1111110 (
b0 '
b0 &
b0 %
b0 $
b1111110 #
b0 "
0!
$end
#5
1!
#10
b1000111 #
b1000111 (
b1111 $
b1111 &
b1111 '
0!
b11110001 "
b11110001 %
#15
b110000 #
b110000 (
b1 $
b1 &
b1 '
1!
#20
b1001111 #
b1001111 (
b1110 $
b1110 &
b1110 '
0!
b11100010 "
b11100010 %
#25
b1101101 #
b1101101 (
b10 $
b10 &
b10 '
1!
#30
b1001111 #
b1001111 (
b1110 $
b1110 &
b1110 '
0!
b11100011 "
b11100011 %
#35
b1111001 #
b1111001 (
b11 $
b11 &
b11 '
1!
#40
b111101 #
b111101 (
b1101 $
b1101 &
b1101 '
0!
b11010100 "
b11010100 %
#45
b110011 #
b110011 (
b100 $
b100 &
b100 '
1!
#50
b1001110 #
b1001110 (
b1100 $
b1100 &
b1100 '
0!
b11000101 "
b11000101 %
#55
b1011011 #
b1011011 (
b101 $
b101 &
b101 '
1!
