project5_Structural Verilog for Combinational Circuits/demux.v
module demux(
    input EN,
    input [1:0] I,
    output reg [3:0] Y
);
always @(EN,I ) 
begin
    if (EN) 
    begin
      case(I)
      2'b00: Y = 4'b0001;
      2'b01: Y = 4'b0010;
      2'b10: Y = 4'b0100;
      2'b11: Y = 4'b1000;
      default: Y = 4'b0000;
      endcase;
    end
    else 
       Y <= 4'b0000;    
end
endmodule

project5_Structural Verilog for Combinational Circuits/mux.v
module mux(
    input [3:0] I,
    input [1:0] S,
    output  Y
);
reg temp;
always @(I,S ) begin
    case (S)
     2'b00 : temp <= I[0];
     2'b01 : temp <= I[1];
     2'b10 : temp <= I[2];
     2'b11 : temp <= I[3];
     default: temp <= 1'b0;
    endcase
    
end
assign Y = temp;
endmodule

project5_Structural Verilog for Combinational Circuits/counter.v
module counter (
	input clk,
	output  Y1, Y0
);

reg [1:0] counter = 2'b00;

always @ (posedge clk)
begin
	counter <= counter + 1;
end


assign Y1 = counter[1];
assign Y0 = counter[0];


endmodule

project5_Structural Verilog for Combinational Circuits/wrapper.v
module wrapper(
    input [3:0]sw,
    input  clk,
    output  [3:0]led
);

wire sdata;
wire [1:0] btn;
counter input_clk(
    .clk(clk),
    .Y1(btn[1]),
    .Y0(btn[0])
);
mux input_mux(
    .I(sw),
    .S(btn),
    .Y(sdata)
);
demux output_demux(
    .EN(sdata),
    .I(btn),
    .Y(led)
);

endmodule

project5_Structural Verilog for Combinational Circuits/wrapper_tb.v
`timescale 1ns / 100ps
module wrapper_tb;
reg [3:0] sw;
reg  clk = 0;
wire [3:0] led;

wrapper name(
     .sw(sw),
     .clk(clk),
     .led(led)
);

always begin
#2 clk = ~clk;
end
initial begin
    $dumpfile("wrapper.vcd");
    $dumpvars(0,name);
    sw = 4'b0000;
    #10 sw = 4'b1101; 
    
    #10 sw = 4'b0010;
   
    #10 sw = 4'b0100;
   
    #10 sw = 4'b1000;
    #100 $stop;
end

endmodule

project5_Structural Verilog for Combinational Circuits/wrapper.vcd
$date
	Sat Apr  2 21:24:36 2022
$end
$version
	Icarus Verilog
$end
$timescale
	100ps
$end
$scope module wrapper_tb $end
$scope module name $end
$var wire 1 ! clk $end
$var wire 4 " sw [3:0] $end
$var wire 1 # sdata $end
$var wire 4 $ led [3:0] $end
$var wire 2 % btn [1:0] $end
$scope module input_clk $end
$var wire 1 ! clk $end
$var wire 1 & Y1 $end
$var wire 1 ' Y0 $end
$var reg 2 ( counter [1:0] $end
$upscope $end
$scope module input_mux $end
$var wire 4 ) I [3:0] $end
$var wire 2 * S [1:0] $end
$var wire 1 # Y $end
$var reg 1 + temp $end
$upscope $end
$scope module output_demux $end
$var wire 1 # EN $end
$var wire 2 , I [1:0] $end
$var reg 4 - Y [3:0] $end
$upscope $end
$upscope $end
$upscope $end
$enddefinitions $end
#0
$dumpvars
b0 -
b0 ,
0+
b0 *
b0 )
b0 (
0'
0&
b0 %
b0 $
0#
b0 "
0!
$end
#20
b1 %
b1 *
b1 ,
1'
b1 (
1!
#40
0!
#60
1&
b10 %
b10 *
b10 ,
0'
b10 (
1!
#80
0!
#100
b11 %
b11 *
b11 ,
1'
b1000 $
b1000 -
b11 (
1#
1+
1!
b1101 "
b1101 )
#120
0!
#140
b1 $
b1 -
0&
b0 %
b0 *
b0 ,
0'
b0 (
1!
#160
0!
#180
0#
0+
b0 $
b0 -
b1 %
b1 *
b1 ,
1'
b1 (
1!
#200
b10 $
b10 -
1#
1+
0!
b10 "
b10 )
#220
0#
0+
b0 $
b0 -
1&
b10 %
b10 *
b10 ,
0'
b10 (
1!
#240
0!
#260
b11 %
b11 *
b11 ,
1'
b11 (
1!
#280
0!
#300
0&
b0 %
b0 *
b0 ,
0'
b0 (
1!
b100 "
b100 )
#320
0!
#340
b1 %
b1 *
b1 ,
1'
b1 (
1!
#360
0!
#380
b100 $
b100 -
1#
1+
1&
b10 %
b10 *
b10 ,
0'
b10 (
1!
#400
b0 $
b0 -
0#
0+
0!
b1000 "
b1000 )
#420
b1000 $
b1000 -
1#
1+
b11 %
b11 *
b11 ,
1'
b11 (
1!
#440
0!
#460
0#
0+
b0 $
b0 -
0&
b0 %
b0 *
b0 ,
0'
b0 (
1!
#480
0!
#500
b1 %
b1 *
b1 ,
1'
b1 (
1!
#520
0!
#540
1&
b10 %
b10 *
b10 ,
0'
b10 (
1!
#560
0!
#580
b1000 $
b1000 -
1#
1+
b11 %
b11 *
b11 ,
1'
b11 (
1!
#600
0!
#620
0#
0+
b0 $
b0 -
0&
b0 %
b0 *
b0 ,
0'
b0 (
1!
#640
0!
#660
b1 %
b1 *
b1 ,
1'
b1 (
1!
#680
0!
#700
1&
b10 %
b10 *
b10 ,
0'
b10 (
1!
#720
0!
#740
b1000 $
b1000 -
1#
1+
b11 %
b11 *
b11 ,
1'
b11 (
1!
#760
0!
#780
0#
0+
b0 $
b0 -
0&
b0 %
b0 *
b0 ,
0'
b0 (
1!
#800
0!
#820
b1 %
b1 *
b1 ,
1'
b1 (
1!
#840
0!
#860
1&
b10 %
b10 *
b10 ,
0'
b10 (
1!
#880
0!
#900
b1000 $
b1000 -
1#
1+
b11 %
b11 *
b11 ,
1'
b11 (
1!
#920
0!
#940
0#
0+
b0 $
b0 -
0&
b0 %
b0 *
b0 ,
0'
b0 (
1!
#960
0!
#980
b1 %
b1 *
b1 ,
1'
b1 (
1!
#1000
0!
#1020
1&
b10 %
b10 *
b10 ,
0'
b10 (
1!
#1040
0!
#1060
b1000 $
b1000 -
1#
1+
b11 %
b11 *
b11 ,
1'
b11 (
1!
#1080
0!
#1100
0#
0+
b0 $
b0 -
0&
b0 %
b0 *
b0 ,
0'
b0 (
1!
#1120
0!
#1140
b1 %
b1 *
b1 ,
1'
b1 (
1!
#1160
0!
#1180
1&
b10 %
b10 *
b10 ,
0'
b10 (
1!
#1200
0!
#1220
b1000 $
b1000 -
1#
1+
b11 %
b11 *
b11 ,
1'
b11 (
1!
#1240
0!
#1260
0#
0+
b0 $
b0 -
0&
b0 %
b0 *
b0 ,
0'
b0 (
1!
#1280
0!
#1300
b1 %
b1 *
b1 ,
1'
b1 (
1!
#1320
0!
#1340
1&
b10 %
b10 *
b10 ,
0'
b10 (
1!
#1360
0!
#1380
b1000 $
b1000 -
1#
1+
b11 %
b11 *
b11 ,
1'
b11 (
1!
